radiotools/__init__.py
radiotools/_version.py
radiotools/info.py
radiotools/version.py
radiotools/analysis/__init__.py
radiotools/analysis/analysis.py
radiotools/cleaning/__init__.py
radiotools/cleaning/clean.py
radiotools/cli_tools/vis.py
radiotools/layouts/__init__.py
radiotools/layouts/layouts.py
radiotools/measurements/__init__.py
radiotools/measurements/measurements.py
radiotools/plotting/__init__.py
radiotools/plotting/utils.py
radiotools/utils/__init__.py
radiotools/utils/utils.py
radiotools/visibility/__init__.py
radiotools/visibility/visibility.py
radionets_radiotools-0.2.1.dist-info/METADATA
radionets_radiotools-0.2.1.dist-info/WHEEL
radionets_radiotools-0.2.1.dist-info/entry_points.txt
radionets_radiotools-0.2.1.dist-info/licenses/LICENSE
radionets_radiotools-0.2.1.dist-info/RECORD
