Metadata-Version: 2.4
Name: radionets-radiotools
Version: 0.2.1
Summary: Tools for radio astronomy.
Author: radionets developers
Maintainer-email: Anno Knierim <anno.knierim@tu-dortmund.de>, Tom Groß <tom.gross@tu-dortmund.de>
License: MIT
License-File: LICENSE
Classifier: Development Status :: 4 - Beta
Classifier: Intended Audience :: Science/Research
Classifier: License :: OSI Approved :: MIT License
Classifier: Programming Language :: Python :: 3
Classifier: Programming Language :: Python :: 3.10
Classifier: Programming Language :: Python :: 3.11
Classifier: Topic :: Scientific/Engineering :: Astronomy
Classifier: Topic :: Scientific/Engineering :: Information Analysis
Classifier: Topic :: Scientific/Engineering :: Physics
Requires-Python: >=3.10
Requires-Dist: astropy>=6.1.0
Requires-Dist: bs4
Requires-Dist: matplotlib~=3.0
Requires-Dist: numpy~=1.16
Requires-Dist: pandas>=2.0
Requires-Dist: python-casacore>=3.7.1
Requires-Dist: requests
Requires-Dist: rich>=13.0
Requires-Dist: toml>=0.10.2
